flake8_import_order/__about__.py
flake8_import_order/__init__.py
flake8_import_order/checker.py
flake8_import_order/flake8_linter.py
flake8_import_order/pylama_linter.py
flake8_import_order/stdlib_list.py
flake8_import_order/styles.py
flake8_import_order-0.19.1.dist-info/licenses/COPYING
flake8_import_order-0.19.1.dist-info/METADATA
flake8_import_order-0.19.1.dist-info/WHEEL
flake8_import_order-0.19.1.dist-info/entry_points.txt
flake8_import_order-0.19.1.dist-info/top_level.txt
flake8_import_order-0.19.1.dist-info/RECORD
