Metadata-Version: 2.4
Name: flake8_import_order
Version: 0.19.1
Summary: Flake8 and pylama plugin that checks the ordering of import statements.
Home-page: https://github.com/PyCQA/flake8-import-order
Author: Alex Stapleton
Author-email: alexs@prol.etari.at
Maintainer: Phil Jones
Maintainer-email: philip.graham.jones+flake8-import@gmail.com
License: LGPLv3
Classifier: Development Status :: 4 - Beta
Classifier: Framework :: Flake8
Classifier: Intended Audience :: Developers
Classifier: Operating System :: OS Independent
Classifier: Programming Language :: Python
Classifier: Programming Language :: Python :: 3
Classifier: Programming Language :: Python :: Implementation :: PyPy
Classifier: Topic :: Software Development :: Libraries :: Python Modules
Classifier: Topic :: Software Development :: Quality Assurance
License-File: COPYING
Requires-Dist: pycodestyle
Requires-Dist: setuptools
Dynamic: license-file
